repoze/xmliter/__init__.py
repoze/xmliter/decorator.py
repoze/xmliter/serializer.py
repoze/xmliter/tests.py
repoze/xmliter/utils.py
repoze_xmliter-2.0a2.dist-info/licenses/LICENSE.txt
repoze_xmliter-2.0a2.dist-info/METADATA
repoze_xmliter-2.0a2.dist-info/WHEEL
repoze_xmliter-2.0a2.dist-info/top_level.txt
repoze_xmliter-2.0a2.dist-info/RECORD
